{"cameraMode":{"drawMode":0,"name":"Shaded","section":"Shading Mode"},"sceneLighting":true,"audioPlay":false,"sceneViewState":{"showFog":true,"showMaterialUpdate":false,"showSkybox":true,"showFlares":true,"showImageEffects":true,"showParticleSystems":true},"in2DMode":false,"pivot":{"x":889.7377319335938,"y":-139.59228515625,"z":834.4434814453125},"rotation":{"x":0.570031464099884,"y":0.00149294245056808,"z":-0.0005260604084469378,"w":0.8220349550247192},"size":7080.3212890625,"orthographic":false}